spacedust/__init__.py
spacedust/core.py
spacedust-0.1.3.dist-info/METADATA
spacedust-0.1.3.dist-info/RECORD
spacedust-0.1.3.dist-info/WHEEL
spacedust-0.1.3.dist-info/top_level.txt
