Metadata-Version: 2.1
Name: spacedust
Version: 0.1.3
Summary: Blows away all that is unnecessary.
Home-page: http://github.com/QCaudron/spacedust
Author: Quentin CAUDRON
Author-email: quentincaudron@gmail.com
License: MIT
Platform: UNKNOWN
Classifier: License :: OSI Approved :: MIT License
Classifier: Programming Language :: Python :: 3.5
Classifier: Programming Language :: Python :: 3.6
Classifier: Programming Language :: Python :: 3.7
Classifier: Development Status :: 4 - Beta
Requires-Dist: numpy (>=1.13)
Requires-Dist: pandas (>=0.22)
Requires-Dist: scikit-learn (>=0.19)
Requires-Dist: xgboost (>=0.80)
